{
  "12monthsboostnitro": "<:12monthsboostnitro:1387742435769061417>",
  "24_months": "<:24_months:1387742436742139974>",
  "2monthsboostnitro": "<:2monthsboostnitro:1387742437723602975>",
  "6months_boost": "<:6months_boost:1387742439477088287>",
  "active_developer": "<:active_developer:1387742440697368606>",
  "balance": "<:balance:1387742461014573058>",
  "boost15month": "<:boost15month:1387742462629511270>",
  "boost1month": "<:boost1month:1387742464202379324>",
  "bravery": "<:bravery:1387742465544687707>",
  "brilliance": "<:brilliance:1387742466697990285>",
  "bughunter": "<:bughunter:1387742487690612887>",
  "bughuntergold": "<:bughuntergold:1387742489338970123>",
  "discord_employee": "<:discord_employee:1387742493046734979>",
  "discord_nitro": "<:discord_nitro:1387742494610952194>",
  "early_supporter": "<:early_supporter:1387742496796315779>",
  "early_verified_bot_developer": "<:early_verified_bot_developer:1387742498226573342>",
  "hypesquad_events": "<:hypesquad_events:1387742522545279056>",
  "moderatorprogramsalumni": "<:moderatorprogramsalumni:1387742524105429032>",
  "nitro_boost_18_months": "<:nitro_boost_18_months:1387742525699260538>",
  "nitro_boost_3_months": "<:nitro_boost_3_months:1387742527339102338>",
  "nitro_boost_9_months": "<:nitro_boost_9_months:1387742529289457674>",
  "oldusername": "<:oldusername:1387742549225115680>",
  "partnered_server_owner": "<:partnered_server_owner:1387742553394253834>",
  "paypal": "<:paypal:1387742555021508629>",
  "bronze": "<:bronze:1387742468727898182>",
  "diamond": "<:diamond:1387742491629060156>",
  "emerald": "<:emerald:1387742518153707570>",
  "gold": "<:gold:1387742520733204480>",
  "opal": "<:opal:1387742550919614496>",
  "platinum": "<:platinum:1387742556649164922>",
  "questbadge": "<:questbadge:1387742558247190629>",
  "ruby": "<:ruby:1387742559970922496>",
  "silver": "<:silver:1387742580300582974>"
}

